aloe_webdriver/__init__.py
aloe_webdriver/css.py
aloe_webdriver/django.py
aloe_webdriver/screenshot_failed.py
aloe_webdriver/util.py
aloe_webdriver/webdriver.py
aloe_webdriver/tests/__init__.py
aloe_webdriver/tests/base.py
aloe_webdriver/tests/test_buttons.py
aloe_webdriver/tests/test_css_selector_steps.py
aloe_webdriver/tests/test_screenshot_failed.py
aloe_webdriver/tests/test_util.py
aloe_webdriver/tests/test_webdriver.py
aloe_webdriver/tests/features/__init__.py
aloe_webdriver/tests/features/steps.py
aloe_webdriver/tests/html_pages/ajax_target.html
aloe_webdriver/tests/html_pages/alert_page.html
aloe_webdriver/tests/html_pages/basic_page.html
aloe_webdriver/tests/html_pages/button_page.html
aloe_webdriver/tests/html_pages/favicon.ico
aloe_webdriver/tests/html_pages/frame_page.html
aloe_webdriver/tests/html_pages/green.png
aloe_webdriver/tests/html_pages/link_dest.html
aloe_webdriver/tests/html_pages/link_page.html
aloe_webdriver/tests/html_pages/tooltips.html
aloe_webdriver-0.6.0.dist-info/LICENSE
aloe_webdriver-0.6.0.dist-info/METADATA
aloe_webdriver-0.6.0.dist-info/WHEEL
aloe_webdriver-0.6.0.dist-info/top_level.txt
aloe_webdriver-0.6.0.dist-info/RECORD
