Metadata-Version: 1.1
Name: aloe-webdriver
Version: 0.6.0
Summary: Selenium webdriver extension for Aloe
Home-page: https://github.com/aloetesting/aloe_webdriver/
Author: Alexey Kotlyarov, Danielle Madeley, Nick Pilon, Ben Bangert
Author-email: a@koterpillar.com, danielle@madeley.id.au, npilon@gmail.com, ben@groovie.org
License: UNKNOWN
Platform: UNKNOWN
Classifier: License :: OSI Approved :: MIT License
Classifier: Programming Language :: Python
Classifier: Programming Language :: Python :: 2
Classifier: Programming Language :: Python :: 3
